[{"lote":"65f8a59a3ac6a58f3521c805","cajas":8,"tipoCaja":"G-37","calibre":150,"calidad":1.5,"fecha":"2024-03-19T19:20:54.819Z"},{"lote":"65f8a59a3ac6a58f3521c805","cajas":1,"tipoCaja":"G-37","calibre":150,"calidad":1.5,"fecha":"2024-03-19T19:21:11.223Z"},{"lote":"65f8a59a3ac6a58f3521c805","cajas":22,"tipoCaja":"G-37","calibre":200,"calidad":1.5,"fecha":"2024-03-19T19:22:10.356Z"},{"lote":"65f9e76364f2f240775170b2","cajas":2,"tipoCaja":"G-37","calibre":150,"calidad":1.5,"fecha":"2024-03-19T20:11:22.729Z"},{"lote":"65f47dcafb8b7ecd552fbc93","cajas":4,"tipoCaja":"B-40","calibre":200,"calidad":1,"fecha":"2024-03-16T17:55:14.003Z"},{"lote":"65f595faf67803306149502b","cajas":9,"tipoCaja":"B-40","calibre":200,"calidad":1,"fecha":"2024-03-18T11:12:00.354Z"},{"lote":"65f824aaf940e589dbb8f9ff","cajas":8,"tipoCaja":"B-40","calibre":200,"calidad":1,"fecha":"2024-03-19T14:30:30.075Z"},{"lote":"65f9e76364f2f240775170b2","cajas":13,"tipoCaja":"B-40","calibre":200,"calidad":1,"fecha":"2024-03-19T20:09:36.014Z"}]